Metadata-Version: 2.1
Name: pymongo-paginate
Version: 1.5
Summary: Package to paginate pymongo queries
Author: Gabriel Martins
License: UNKNOWN
Project-URL: Source, https://github.com/gabrielmrts/pymongo-paginate
Platform: UNKNOWN
Classifier: Programming Language :: Python :: 3
Classifier: License :: OSI Approved :: MIT License
Classifier: Operating System :: OS Independent
Requires-Python: >=3.6
